mcp_filesystem_extra/__init__.py
mcp_filesystem_extra/server.py
mcp_filesystem_extra-0.0.2.dist-info/METADATA
mcp_filesystem_extra-0.0.2.dist-info/WHEEL
mcp_filesystem_extra-0.0.2.dist-info/entry_points.txt
mcp_filesystem_extra-0.0.2.dist-info/licenses/LICENSE
mcp_filesystem_extra-0.0.2.dist-info/licenses/NOTICE
mcp_filesystem_extra-0.0.2.dist-info/RECORD
