Metadata-Version: 2.4
Name: mcp-filesystem-extra
Version: 0.0.2
Summary: MCP server exposing additional filesystem tools.
Author: AI/Run Team
Maintainer: AI/Run Team
License: MIT
License-File: LICENSE
License-File: NOTICE
Keywords: append,filesystem,mcp
Requires-Python: >=3.10
Requires-Dist: mcp>=1.0.0
Requires-Dist: mcp[cli]>=1.9.2
Requires-Dist: pydantic>=2.0.0
